kedro_init-0.1.0.dist-info/METADATA
kedro_init-0.1.0.dist-info/WHEEL
kedro_init-0.1.0.dist-info/entry_points.txt
kedro_init-0.1.0.dist-info/licenses/LICENSE
kedro_init/__init__.py
kedro_init/build_config.py
kedro_init/cli.py
kedro_init/config_dirs.py
kedro_init/init.py
kedro_init/modules.py
kedro_init/py.typed
kedro_init/templates/pipeline_registry.py
kedro_init/templates/settings.py
kedro_init-0.1.0.dist-info/RECORD
