Metadata-Version: 2.1
Name: kedro-init
Version: 0.1.0
Summary: A simple CLI command that initialises a Kedro project from an existing Python package
Author-Email: =?utf-8?q?Juan_Luis_Cano_Rodr=C3=ADguez?= <juan_luis_cano@mckinsey.com>
License: Copyright (c) 2023 by Juan Luis Cano Rodríguez <juan_luis_cano@mckinsey.com>
Classifier: Development Status :: 3 - Alpha
Classifier: Intended Audience :: Developers
Classifier: License :: OSI Approved :: MIT License
Classifier: Operating System :: OS Independent
Classifier: Programming Language :: Python
Classifier: Programming Language :: Python :: 3
Classifier: Programming Language :: Python :: 3.9
Classifier: Programming Language :: Python :: 3.10
Classifier: Programming Language :: Python :: 3.11
Classifier: Programming Language :: Python :: 3.12
Project-URL: Source, https://github.com/astrojuanlu/kedro-init
Project-URL: Tracker, https://github.com/astrojuanlu/kedro-init/issues
Project-URL: Documentation, https://kedro-init.readthedocs.io
Requires-Python: >=3.9
Requires-Dist: click
Requires-Dist: installer
Requires-Dist: kedro>=0.18.14
Requires-Dist: pygetimportables>=0.2.1
Requires-Dist: tomlkit
Requires-Dist: rich; extra == "rich"
Requires-Dist: mypy; extra == "test"
Requires-Dist: hypothesis; extra == "test"
Requires-Dist: pytest; extra == "test"
Requires-Dist: pytest-cov; extra == "test"
Requires-Dist: furo; extra == "doc"
Requires-Dist: myst-parser; extra == "doc"
Requires-Dist: sphinx>=5; extra == "doc"
Requires-Dist: sphinx-copybutton; extra == "doc"
Provides-Extra: rich
Provides-Extra: test
Provides-Extra: doc
